{
  "id": 104,
  "name": "마스터 4",
  "cols": 6,
  "rows": 9,
  "timeLimit": 55,
  "hintCount": 1,
  "targetScore": 0,
  "starThresholds": [
    1500,
    3600,
    5900
  ],
  "initialBoard": [
    [
      9,
      8,
      7,
      5,
      9,
      4
    ],
    [
      3,
      9,
      3,
      9,
      9,
      7
    ],
    [
      4,
      2,
      7,
      0,
      9,
      7
    ],
    [
      4,
      5,
      4,
      5,
      9,
      1
    ],
    [
      2,
      4,
      9,
      6,
      6,
      6
    ],
    [
      3,
      5,
      9,
      6,
      9,
      4
    ],
    [
      6,
      3,
      7,
      8,
      7,
      2
    ],
    [
      9,
      7,
      8,
      2,
      3,
      7
    ],
    [
      3,
      8,
      9,
      7,
      7,
      5
    ]
  ],
  "initialLives": [
    [
      1,
      1,
      1,
      1,
      1,
      1
    ],
    [
      1,
      1,
      1,
      1,
      1,
      1
    ],
    [
      1,
      1,
      1,
      0,
      1,
      1
    ],
    [
      1,
      1,
      1,
      4,
      1,
      1
    ],
    [
      2,
      4,
      1,
      3,
      2,
      1
    ],
    [
      1,
      1,
      1,
      1,
      1,
      1
    ],
    [
      1,
      1,
      1,
      1,
      1,
      1
    ],
    [
      1,
      1,
      4,
      1,
      1,
      1
    ],
    [
      1,
      1,
      2,
      1,
      1,
      3
    ]
  ],
  "initialObstacles": [
    [
      0,
      0,
      0,
      0,
      0,
      0
    ],
    [
      0,
      0,
      0,
      0,
      0,
      0
    ],
    [
      0,
      0,
      0,
      1,
      0,
      0
    ],
    [
      0,
      0,
      0,
      0,
      0,
      0
    ],
    [
      0,
      0,
      0,
      0,
      0,
      0
    ],
    [
      0,
      0,
      0,
      0,
      0,
      0
    ],
    [
      0,
      0,
      0,
      0,
      0,
      0
    ],
    [
      0,
      0,
      0,
      0,
      0,
      0
    ],
    [
      0,
      0,
      0,
      0,
      0,
      0
    ]
  ]
}
